netoi_check/__init__.py
netoi_check-0.5.dist-info/DESCRIPTION.rst
netoi_check-0.5.dist-info/METADATA
netoi_check-0.5.dist-info/RECORD
netoi_check-0.5.dist-info/WHEEL
netoi_check-0.5.dist-info/entry_points.txt
netoi_check-0.5.dist-info/metadata.json
netoi_check-0.5.dist-info/top_level.txt
