Metadata-Version: 2.0
Name: netoi-check
Version: 0.5
Summary: CLI for solution submission to NetOI
Home-page: http://github.com/lionell/netoi-check
Author: Ruslan Sakevych
Author-email: xlionell@gmail.com
License: MIT
Platform: UNKNOWN
Requires-Dist: requests
Requires-Dist: lxml
Requires-Dist: tabulate
